mlpce/Confidence.py
mlpce/__init__.py
mlpce/helpers.py
mlpce/version.py
mlpce-0.2.0.dist-info/LICENSE
mlpce-0.2.0.dist-info/METADATA
mlpce-0.2.0.dist-info/WHEEL
mlpce-0.2.0.dist-info/top_level.txt
mlpce-0.2.0.dist-info/RECORD
