Metadata-Version: 2.1
Name: mlpce
Version: 0.2.0
Summary: Machine Learning Prediction Confidence Estimation
Home-page: https://github.com/bmewing/mlpce
Author: Mark Ewing
Author-email: b.mark@ewingsonline.com
License: MIT
Keywords: machine learning,prediction,prediction variance,confidence
Platform: UNKNOWN
Classifier: Programming Language :: Python :: 3
Classifier: License :: OSI Approved :: MIT License
Classifier: Operating System :: OS Independent
Requires-Dist: numpy
Requires-Dist: pandas
